knowldad/__init__.py
knowldad/knowldad.py
knowldad-0.0.1.dist-info/METADATA
knowldad-0.0.1.dist-info/WHEEL
knowldad-0.0.1.dist-info/top_level.txt
knowldad-0.0.1.dist-info/RECORD
