Metadata-Version: 2.1
Name: knowldad
Version: 0.0.1
Requires-Dist: crawldad >=0.0.2
